ask_schools/__init__.py
ask_schools-0.3.6.dist-info/WHEEL
ask_schools-0.3.6.dist-info/METADATA
ask_schools-0.3.6.dist-info/RECORD
