Metadata-Version: 2.1
Name: ask-schools
Version: 0.3.6
Summary: Ask Scholars Portal School Name Conversion
Home-page: https://github.com/guinslym/ask_schools
License: MIT
Keywords: Ask,Scholars Portal,Ontario
Author: Guinsly Mondesir
Author-email: guinslym@gmail.com
Requires-Python: >=3.4,<4.0
Classifier: License :: OSI Approved :: MIT License
Classifier: Operating System :: OS Independent
Classifier: Programming Language :: Python :: 3
Classifier: Programming Language :: Python :: 3.4
Classifier: Programming Language :: Python :: 3.5
Classifier: Programming Language :: Python :: 3.6
Classifier: Programming Language :: Python :: 3.7
Classifier: Programming Language :: Python :: 3.8
Classifier: Topic :: Software Development :: Documentation
Classifier: Topic :: Software Development :: Libraries :: Python Modules
Classifier: Topic :: Software Development :: Quality Assurance
Project-URL: Repository, https://github.com/guinslym/ask_schools
